yafe/__init__.py
yafe/base.py
yafe/utils.py
yafe/tests/__init__.py
yafe/tests/script_for_generate_oar_script.py
yafe/tests/test_base.py
yafe/tests/test_utils.py
yafe-1.0.3.dist-info/DESCRIPTION.rst
yafe-1.0.3.dist-info/METADATA
yafe-1.0.3.dist-info/RECORD
yafe-1.0.3.dist-info/WHEEL
yafe-1.0.3.dist-info/metadata.json
yafe-1.0.3.dist-info/top_level.txt
