Metadata-Version: 2.0
Name: yafe
Version: 1.0.3
Summary: Yet Another Framework for Experiments
Home-page: https://gitlab.lis-lab.fr/skmad-suite/yafe
Author: Ronan Hamon, Valentin Emiya, and Florent Jaillet
Author-email: ronan.hamon@lis-lab.fr, valentin.emiya@lis-lab.fr, florent.jaillet@lis-lab.fr
License: GNU General Public License v3 (GPLv3)
Keywords: audio,data structures,missing data
Platform: UNKNOWN
Classifier: Development Status :: 5 - Production/Stable
Classifier: Intended Audience :: Developers
Classifier: Intended Audience :: End Users/Desktop
Classifier: Intended Audience :: Science/Research
Classifier: Topic :: Scientific/Engineering :: Mathematics
Classifier: License :: OSI Approved :: GNU General Public License v3 (GPLv3)
Classifier: Natural Language :: English
Classifier: Operating System :: MacOS :: MacOS X 
Classifier: Operating System :: POSIX :: Linux
Classifier: Programming Language :: Python :: 3.5
Classifier: Programming Language :: Python :: 3.6
Requires-Python: >=3.5
Requires-Dist: numpy
Provides-Extra: dev
Requires-Dist: coverage; extra == 'dev'
Requires-Dist: pytest; extra == 'dev'
Requires-Dist: pytest-cov; extra == 'dev'
Requires-Dist: pytest-randomly; extra == 'dev'
Provides-Extra: doc
Requires-Dist: nbsphinx; extra == 'doc'
Requires-Dist: numpydoc; extra == 'doc'
Requires-Dist: sphinx; extra == 'doc'
Provides-Extra: xarray
Requires-Dist: xarray; extra == 'xarray'
